odoo8_addon_web_one2many_list_action-8.0.1.0.0-py2.7-nspkg.pth
odoo_addons/web_one2many_list_action/__openerp__.py
odoo_addons/web_one2many_list_action/assets.xml
odoo_addons/web_one2many_list_action/__init__.py
odoo_addons/web_one2many_list_action/README.rst
odoo_addons/web_one2many_list_action/static/description/icon.png
odoo_addons/web_one2many_list_action/static/src/js/views.js
odoo8_addon_web_one2many_list_action-8.0.1.0.0.dist-info/top_level.txt
odoo8_addon_web_one2many_list_action-8.0.1.0.0.dist-info/WHEEL
odoo8_addon_web_one2many_list_action-8.0.1.0.0.dist-info/RECORD
odoo8_addon_web_one2many_list_action-8.0.1.0.0.dist-info/metadata.json
odoo8_addon_web_one2many_list_action-8.0.1.0.0.dist-info/DESCRIPTION.rst
odoo8_addon_web_one2many_list_action-8.0.1.0.0.dist-info/METADATA
odoo8_addon_web_one2many_list_action-8.0.1.0.0.dist-info/namespace_packages.txt
